hardware/de0-mikrorechner/src/3_Execution/alu.vhd
library ieee; 
use ieee.std_logic_1164.all;
use ieee.numeric_std.all;
library work;
use work.alu_opcode.all;

entity alu is
   port( opA, opB: in signed(31 downto 0);
         result: out  signed(31 downto 0);
		 op: in STD_LOGIC_VECTOR(4 downto 0);
		 zero: out STD_LOGIC);
end entity alu;

architecture behaviour of alu is
  begin
    alu_prozess : process (opA, opB, op) is
		variable shift: signed(31 downto 0);
      begin
		zero <= '0';
	
       case op is 
		when alu_mov => 
			result <= opA;
			if opA = 0 then
				zero <= '1';
			end if;
	    when alu_add => 
			result <= opA + opB;
			if opA + opB = 0 then
				zero <= '1';
			end if;
		when alu_sub => 
			result <= opA - opB;
			if opA - opB = 0 then
				zero <= '1';
			end if;
	    when alu_lsl => 
			shift := opA;
--			for i in to_integer(opB) downto 1 loop
				shift := shift(30 downto 0) & '0';
--			end loop;
			result <= shift;
			if shift = 0 then
				zero <= '1';
			end if;
		when alu_lsr => 
			shift := opA;
--			for i in to_Integer(opB) downto 1 loop
				shift := '0' & shift(31 downto 1);
--			end loop;
			result <= shift;
			if shift = 0 then
				zero <= '1';
			end if;
		when alu_asr => 
				shift := opA;
--			for i in to_integer(opB) downto 1 loop
				shift := shift(31) & shift(31 downto 1);
--			end loop;
			result <= shift;
			if shift = 0 then
				zero <= '1';
			end if;
		when alu_and => 
			result <= opA AND opB; --and
			if (opA AND opB) = 0 then
				zero <= '1';
			end if;
		when alu_or => 
			result <= opA OR opB; --or
			if (opA OR opB) = 0 then
				zero <= '1';
			end if;
		when alu_xor =>
			result <= opA XOR opB; --or
			if (opA XOR opB) = 0 then
				zero <= '1';
			end if;
		when alu_not => 
			result <= NOT opA; --not
			if (NOT opA) = 0 then
				zero <= '1';
			end if;
		when alu_cmpe => if opA = opB then result <= "00000000000000000000000000000001"; -- cmpe
		else result <= "00000000000000000000000000000000"; -- cmpe else
		zero <= '1';
		end if;

		when alu_cmpne => if opA /= opB then result <= "00000000000000000000000000000001"; -- compne 
		else result <= "00000000000000000000000000000000"; -- compne else
		zero <= '1';
		end if;

		when alu_cmpgt => if opA > opB then result <= "00000000000000000000000000000001"; --cmpgt
		else result <= "00000000000000000000000000000000"; --cmpgt else
		zero <= '1';
		end if;

		when alu_cmpgt_u => if unsigned(opA) > unsigned(opB) then result <= "00000000000000000000000000000001"; --cmpgt
		else result <= "00000000000000000000000000000000"; --cmpgt else
		zero <= '1';
		end if;

		when alu_cmplt => if opA < opB then result <= "00000000000000000000000000000001"; --cmplt
		else result <= "00000000000000000000000000000000"; --cmplt else
		zero <= '1';
		end if;

		when alu_cmplt_u => if unsigned(opA) < unsigned(opB) then result <= "00000000000000000000000000000001"; --cmplt
		else result <= "00000000000000000000000000000000"; --cmplt else
		zero <= '1';
		end if;

		when alu_shi => 
			result <= opB(31 downto 16) & opA(15 downto 0);
			if opB(31 downto 16) & opA(15 downto 0) = 0 then
				zero <= '1';
			end if;

		when alu_slo => 
			result <= opA(31 downto 16) & opB(15 downto 0);
			if opA(31 downto 16) & opB(15 downto 0) = 0 then
				zero <= '1';
			end if;

	    when others => 
			result <= opA; --default
			if opA = 0 then
				zero <= '1';
			end if;
	end case;
	end process alu_prozess;
end behaviour;		  

	  
-- TODO 
-- input a, input b, input op, output result def
-- prozess intitalisieren aka konstrukt einfach bauen
-- überlegen wie amn logischen shift nach rechts umsetzt
-- imports der library
-- prüfen ob da select hinkommen

-- mux integrieren in die alus -> erster ansatz sonst extern verlagern

hardware/code/3_Execution/aluTest.vhd
library ieee;
use ieee.std_logic_1164.all;
use ieee.numeric_std.all;
library work;
use work.alu_opcode.all;

entity aluTest is
    generic(	
        periodC	: time		:= 10 ns;
        cyclesC	: integer	:= 100);
    end entity aluTest;

architecture testbench of aluTest is

    component alu is
        port( opA, opB: in signed(31 downto 0);
         result: out  signed(31 downto 0);
		 op: in STD_LOGIC_VECTOR(4 downto 0);
         zero: out STD_LOGIC);
    end component alu;   

    signal opA, opB, result	: signed(31 downto 0);
    signal op		        : STD_LOGIC_VECTOR(4 downto 0);
    signal zero             : STD_LOGIC;

    
begin
    aluI: alu	port map (opA, opB, result, op, zero);

    aluP: process is
    begin
    opA <= to_signed(100, 32);
    opB <= to_signed(4, 32);
    
    op <= alu_mov;
	wait for periodC;
    op <= alu_add;
	wait for periodC;
    op <= alu_sub;
    wait for periodC;
    op <= alu_lsl;
	wait for periodC;
    op <= alu_lsr;
	wait for periodC;
    op <= alu_asr;
	wait for periodC;
    op <= alu_and;
	wait for periodC;
    op <= alu_or;
    wait for periodC;
    op <= alu_xor;
	wait for periodC;
    op <= alu_not;
	wait for periodC;
    op <= alu_cmpe;
	wait for periodC;
    op <= alu_cmpne;
	wait for periodC;
    op <= alu_cmpgt;
	wait for periodC;
    op <= alu_cmpgt_u;
	wait for periodC;
    op <= alu_cmplt;
	wait for periodC;
    op <= alu_cmplt_u;
	wait for periodC;
    wait;
end process aluP;
end architecture testbench;

hardware/de0-mikrorechner/sim/ghdl/work/aluTest.vcd
$date
  Thu Jan 29 13:10:31 2026
$end
$version
  GHDL v0
$end
$timescale
  1 fs
$end
$scope module standard $end
$upscope $end
$scope module std_logic_1164 $end
$upscope $end
$scope module numeric_std $end
$upscope $end
$scope module alu_opcode $end
$upscope $end
$scope module alutest $end
$var reg 32 ! opa[31:0] $end
$var reg 32 " opb[31:0] $end
$var reg 32 # result[31:0] $end
$var reg 5 $ op[4:0] $end
$var reg 1 % zero $end
$scope module alui $end
$var reg 32 & opa[31:0] $end
$var reg 32 ' opb[31:0] $end
$var reg 32 ( result[31:0] $end
$var reg 5 ) op[4:0] $end
$var reg 1 * zero $end
$upscope $end
$upscope $end
$enddefinitions $end
#0
b00000000000000000000000001100100 !
b00000000000000000000000000000100 "
b00000000000000000000000001100100 #
b00000 $
0%
b00000000000000000000000001100100 &
b00000000000000000000000000000100 '
b00000000000000000000000001100100 (
b00000 )
0*
#10000000
b00000000000000000000000001101000 #
b00001 $
b00000000000000000000000001101000 (
b00001 )
#20000000
b00000000000000000000000001100000 #
b00010 $
b00000000000000000000000001100000 (
b00010 )
#30000000
b00000000000000000000011001000000 #
b00011 $
b00000000000000000000011001000000 (
b00011 )
#40000000
b00000000000000000000000000000110 #
b00100 $
b00000000000000000000000000000110 (
b00100 )
#50000000
b00101 $
b00101 )
#60000000
b00000000000000000000000000000100 #
b00110 $
b00000000000000000000000000000100 (
b00110 )
#70000000
b00000000000000000000000001100100 #
b00111 $
b00000000000000000000000001100100 (
b00111 )
#80000000
b00000000000000000000000001100000 #
b01000 $
b00000000000000000000000001100000 (
b01000 )
#90000000
b11111111111111111111111110011011 #
b01001 $
b11111111111111111111111110011011 (
b01001 )
#100000000
b00000000000000000000000000000000 #
b01010 $
1%
b00000000000000000000000000000000 (
b01010 )
1*
#110000000
b00000000000000000000000000000001 #
b01011 $
0%
b00000000000000000000000000000001 (
b01011 )
0*
#120000000
b01100 $
b01100 )
#130000000
b01101 $
b01101 )
#140000000
b00000000000000000000000000000000 #
b01110 $
1%
b00000000000000000000000000000000 (
b01110 )
1*
#150000000
b01111 $
b01111 )
1*
